jwst_mast_query/__init__.py
jwst_mast_query/jwst_download.py
jwst_mast_query/jwst_query.cfg
jwst_mast_query/jwst_query.py
jwst_mast_query/pdastro.py
jwst_mast_query/sortable.js
jwst_mast_query/version.py
jwst_mast_query/scripts/jwst_download.py
jwst_mast_query/tests/test_jwst_download.py
jwst_mast_query/tests/testing_config_files/1063_obs108_query.cfg
jwst_mast_query/tests/testing_config_files/1068_obs34_query.cfg
jwst_mast_query/tests/testing_config_files/1068_obs3_query_guidestars_only.cfg
jwst_mast_query/tests/testing_config_files/1068_obs3_query_with_guidestars.cfg
jwst_mast_query/utils/constants.py
jwst_mast_query-0.0.6.dist-info/LICENSE.txt
jwst_mast_query-0.0.6.dist-info/METADATA
jwst_mast_query-0.0.6.dist-info/WHEEL
jwst_mast_query-0.0.6.dist-info/entry_points.txt
jwst_mast_query-0.0.6.dist-info/top_level.txt
jwst_mast_query-0.0.6.dist-info/RECORD
