Metadata-Version: 2.1
Name: jwst_mast_query
Version: 0.0.6
Summary: Query MAST for data products from the James Webb Space Telescope, and download them
Author-email: Armin Rest <arest@stsci.edu>, Bryan Hilbert <bhilbert@stsci.edu>, Association of Universities for Research in Astronomy <help@stsci.edu>
License: BSD 3-Clause License
Project-URL: github_project, https://github.com/spacetelescope/jwst_mast_query
Keywords: astronomy
Classifier: Intended Audience :: Science/Research
Classifier: License :: OSI Approved :: BSD License
Classifier: Operating System :: OS Independent
Classifier: Programming Language :: Python
Classifier: Topic :: Scientific/Engineering :: Astronomy
Classifier: Topic :: Software Development :: Libraries :: Python Modules
Requires-Python: >=3.10
License-File: LICENSE.txt
Requires-Dist: numpy>=1.21.6
Requires-Dist: scipy>=1.5.0
Requires-Dist: matplotlib>=3.2.0
Requires-Dist: astropy>=5.1.0
Requires-Dist: photutils>=1.10.0
Requires-Dist: poppy>=1.0.0
Requires-Dist: pysiaf>=0.19.1
Requires-Dist: synphot>=1.0.0
Requires-Dist: astroquery>=0.4.6
Provides-Extra: test
Requires-Dist: pytest; extra == "test"
Provides-Extra: docs
Requires-Dist: nbsphinx; extra == "docs"
Requires-Dist: sphinx; extra == "docs"
Requires-Dist: sphinx-automodapi; extra == "docs"
Requires-Dist: sphinx-rtd-theme; extra == "docs"
Requires-Dist: stsci-rtd-theme; extra == "docs"
Requires-Dist: extension-helpers; extra == "docs"
